[
    {
        "type": "FeatureCollection",
        "features": [
            {
                "type": "Feature",
                "geometry": {
                    "type": "Point",
                    "coordinates": [
                        21862.083704744553,
                        35751.58601769997
                    ]
                },
                "properties": {
                    "type": "origin",
                    "rotation": 0.39603900942059145
                }
            },
            {
                "type": "Feature",
                "geometry": {
                    "type": "Point",
                    "coordinates": [
                        28295.79428838387,
                        37499.27489336423
                    ]
                },
                "properties": {
                    "type": "destination"
                }
            },
            {
                "type": "Feature",
                "geometry": {
                    "type": "Polygon",
                    "coordinates": [
                        [
                            [
                                28240.23726508191,
                                37582.42185459448
                            ],
                            [
                                28248.65461470127,
                                37587.46701979906
                            ],
                            [
                                28257.487227357797,
                                37591.64453446469
                            ],
                            [
                                28286.72593307741,
                                37558.72709119977
                            ],
                            [
                                28278.426942309463,
                                37548.439613159244
                            ],
                            [
                                28234.166837805704,
                                37577.91971888898
                            ],
                            [
                                28240.23726508191,
                                37582.42185459448
                            ]
                        ]
                    ]
                },
                "properties": {
                    "type": "mask"
                }
            }
        ]
    },
    {
        "type": "FeatureCollection",
        "features": [
            {
                "type": "Feature",
                "geometry": {
                    "type": "Point",
                    "coordinates": [
                        21151.9868612008,
                        36386.87896336451
                    ]
                },
                "properties": {
                    "type": "origin",
                    "rotation": 0.2351472481566914
                }
            },
            {
                "type": "Feature",
                "geometry": {
                    "type": "Point",
                    "coordinates": [
                        28261.740786917824,
                        37505.60055235352
                    ]
                },
                "properties": {
                    "type": "destination"
                }
            },
            {
                "type": "Feature",
                "geometry": {
                    "type": "Polygon",
                    "coordinates": [
                        [
                            [
                                28288.939177777233,
                                37557.195648087276
                            ],
                            [
                                28286.334337851094,
                                37543.172773886545
                            ],
                            [
                                28278.426942309463,
                                37548.439613159244
                            ],
                            [
                                28286.72593307741,
                                37558.72709119977
                            ],
                            [
                                28288.939177777233,
                                37557.195648087276
                            ]
                        ]
                    ]
                },
                "properties": {
                    "type": "mask"
                }
            }
        ]
    },
    {
        "type": "FeatureCollection",
        "features": [
            {
                "type": "Feature",
                "geometry": {
                    "type": "Point",
                    "coordinates": [
                        21865.547479925553,
                        35758.68834011264
                    ]
                },
                "properties": {
                    "type": "origin",
                    "rotation": -0.25942347746535344
                }
            },
            {
                "type": "Feature",
                "geometry": {
                    "type": "Point",
                    "coordinates": [
                        28260.447953194674,
                        37502.4221155896
                    ]
                },
                "properties": {
                    "type": "destination"
                }
            },
            {
                "type": "Feature",
                "geometry": {
                    "type": "Polygon",
                    "coordinates": [
                        [
                            [
                                28304.682106123964,
                                37552.259630217995
                            ],
                            [
                                28323.26376078564,
                                37534.476622581446
                            ],
                            [
                                28315.569540649947,
                                37523.700229047274
                            ],
                            [
                                28286.334337851094,
                                37543.172773886545
                            ],
                            [
                                28288.939177777233,
                                37557.195648087276
                            ],
                            [
                                28304.682106123964,
                                37552.259630217995
                            ]
                        ]
                    ]
                },
                "properties": {
                    "type": "mask"
                }
            }
        ]
    },
    {
        "type": "FeatureCollection",
        "features": [
            {
                "type": "Feature",
                "geometry": {
                    "type": "Point",
                    "coordinates": [
                        21867.26460799277,
                        35762.238271243885
                    ]
                },
                "properties": {
                    "type": "origin",
                    "rotation": 0.20605037444165952
                }
            },
            {
                "type": "Feature",
                "geometry": {
                    "type": "Point",
                    "coordinates": [
                        28286.923248302228,
                        37494.8557976371
                    ]
                },
                "properties": {
                    "type": "destination"
                }
            },
            {
                "type": "Feature",
                "geometry": {
                    "type": "Polygon",
                    "coordinates": [
                        [
                            [
                                28267.414216100617,
                                37592.93432567742
                            ],
                            [
                                28271.070114289985,
                                37593.47662694568
                            ],
                            [
                                28319.594368052163,
                                37564.067176476514
                            ],
                            [
                                28304.682106123964,
                                37552.259630217995
                            ],
                            [
                                28288.939177777233,
                                37557.195648087276
                            ],
                            [
                                28286.72593307741,
                                37558.72709119977
                            ],
                            [
                                28258.356795214626,
                                37590.66555985252
                            ],
                            [
                                28267.414216100617,
                                37592.93432567742
                            ]
                        ]
                    ]
                },
                "properties": {
                    "type": "mask"
                }
            }
        ]
    },
    {
        "type": "FeatureCollection",
        "features": [
            {
                "type": "Feature",
                "geometry": {
                    "type": "Point",
                    "coordinates": [
                        21662.638216689975,
                        35808.53364794825
                    ]
                },
                "properties": {
                    "type": "origin",
                    "rotation": -0.07982641763989795
                }
            },
            {
                "type": "Feature",
                "geometry": {
                    "type": "Point",
                    "coordinates": [
                        28237.941438275884,
                        37519.03952430029
                    ]
                },
                "properties": {
                    "type": "destination"
                }
            },
            {
                "type": "Feature",
                "geometry": {
                    "type": "Polygon",
                    "coordinates": [
                        [
                            [
                                28337.547868126483,
                                37511.02821986598
                            ],
                            [
                                28322.0557323072,
                                37488.33963932757
                            ],
                            [
                                28310.94065493618,
                                37495.120902139635
                            ],
                            [
                                28325.482147785995,
                                37517.09778854912
                            ],
                            [
                                28315.569540649947,
                                37523.700229047274
                            ],
                            [
                                28323.26376078564,
                                37534.476622581446
                            ],
                            [
                                28337.8109429244,
                                37521.69581820265
                            ],
                            [
                                28337.941438275884,
                                37519.03952430029
                            ],
                            [
                                28337.547868126483,
                                37511.02821986598
                            ]
                        ]
                    ]
                },
                "properties": {
                    "type": "mask"
                }
            }
        ]
    },
    {
        "type": "FeatureCollection",
        "features": [
            {
                "type": "Feature",
                "geometry": {
                    "type": "Point",
                    "coordinates": [
                        21160.166295722367,
                        36373.862705979904
                    ]
                },
                "properties": {
                    "type": "origin",
                    "rotation": 0.2646129476893355
                }
            },
            {
                "type": "Feature",
                "geometry": {
                    "type": "Point",
                    "coordinates": [
                        28258.70229824892,
                        37499.58242442143
                    ]
                },
                "properties": {
                    "type": "destination"
                }
            },
            {
                "type": "Feature",
                "geometry": {
                    "type": "Polygon",
                    "coordinates": [
                        [
                            [
                                28346.894424683756,
                                37546.72209810403
                            ],
                            [
                                28351.09025150005,
                                37537.85076765794
                            ],
                            [
                                28352.731217311335,
                                37533.264575449335
                            ],
                            [
                                28342.199285913284,
                                37517.840325588826
                            ],
                            [
                                28323.26376078564,
                                37534.476622581446
                            ],
                            [
                                28304.682106123964,
                                37552.259630217995
                            ],
                            [
                                28319.594368052163,
                                37564.067176476514
                            ],
                            [
                                28346.142173610137,
                                37547.97715319766
                            ],
                            [
                                28346.894424683756,
                                37546.72209810403
                            ]
                        ]
                    ]
                },
                "properties": {
                    "type": "mask"
                }
            }
        ]
    },
    {
        "type": "FeatureCollection",
        "features": [
            {
                "type": "Feature",
                "geometry": {
                    "type": "Point",
                    "coordinates": [
                        21457.873185533823,
                        36210.66124966255
                    ]
                },
                "properties": {
                    "type": "origin",
                    "rotation": 0.18416656739664372
                }
            },
            {
                "type": "Feature",
                "geometry": {
                    "type": "Point",
                    "coordinates": [
                        28205.63039667127,
                        37584.255848729765
                    ]
                },
                "properties": {
                    "type": "destination"
                }
            },
            {
                "type": "Feature",
                "geometry": {
                    "type": "Polygon",
                    "coordinates": [
                        [
                            [
                                28222.674651941874,
                                37611.50965134768
                            ],
                            [
                                28228.803252541467,
                                37619.093613930636
                            ],
                            [
                                28238.12298477987,
                                37613.44513543997
                            ],
                            [
                                28257.487227357797,
                                37591.64453446469
                            ],
                            [
                                28248.65461470127,
                                37587.46701979906
                            ],
                            [
                                28240.23726508191,
                                37582.42185459448
                            ],
                            [
                                28234.166837805704,
                                37577.91971888898
                            ],
                            [
                                28217.52106864283,
                                37589.006882834394
                            ],
                            [
                                28225.822537606422,
                                37599.19264271565
                            ],
                            [
                                28222.674651941874,
                                37611.50965134768
                            ]
                        ]
                    ]
                },
                "properties": {
                    "type": "mask"
                }
            }
        ]
    },
    {
        "type": "FeatureCollection",
        "features": [
            {
                "type": "Feature",
                "geometry": {
                    "type": "Point",
                    "coordinates": [
                        21457.873185533823,
                        36210.66124966255
                    ]
                },
                "properties": {
                    "type": "origin",
                    "rotation": 0.10735842111563099
                }
            },
            {
                "type": "Feature",
                "geometry": {
                    "type": "Point",
                    "coordinates": [
                        28207.622143067027,
                        37587.06912420117
                    ]
                },
                "properties": {
                    "type": "destination"
                }
            },
            {
                "type": "Feature",
                "geometry": {
                    "type": "Polygon",
                    "coordinates": [
                        [
                            [
                                28267.414216100617,
                                37592.93432567742
                            ],
                            [
                                28258.356795214626,
                                37590.66555985252
                            ],
                            [
                                28238.12298477987,
                                37613.44513543997
                            ],
                            [
                                28271.070114289985,
                                37593.47662694568
                            ],
                            [
                                28267.414216100617,
                                37592.93432567742
                            ]
                        ]
                    ]
                },
                "properties": {
                    "type": "mask"
                }
            }
        ]
    },
    {
        "type": "FeatureCollection",
        "features": [
            {
                "type": "Feature",
                "geometry": {
                    "type": "Point",
                    "coordinates": [
                        21855.067595308017,
                        35737.263293198615
                    ]
                },
                "properties": {
                    "type": "origin",
                    "rotation": 0.5118152162845632
                }
            },
            {
                "type": "Feature",
                "geometry": {
                    "type": "Point",
                    "coordinates": [
                        28304.80808228238,
                        37493.50933391395
                    ]
                },
                "properties": {
                    "type": "destination"
                }
            },
            {
                "type": "Feature",
                "geometry": {
                    "type": "Polygon",
                    "coordinates": [
                        [
                            [
                                28337.941438275884,
                                37519.03952430029
                            ],
                            [
                                28337.8109429244,
                                37521.69581820265
                            ],
                            [
                                28342.199285913284,
                                37517.840325588826
                            ],
                            [
                                28337.547868126483,
                                37511.02821986598
                            ],
                            [
                                28337.941438275884,
                                37519.03952430029
                            ]
                        ]
                    ]
                },
                "properties": {
                    "type": "mask"
                }
            }
        ]
    },
    {
        "type": "FeatureCollection",
        "features": [
            {
                "type": "Feature",
                "geometry": {
                    "type": "Point",
                    "coordinates": [
                        21008.707894035917,
                        35900.85024217685
                    ]
                },
                "properties": {
                    "type": "origin",
                    "rotation": 2.518876125389883
                }
            },
            {
                "type": "Feature",
                "geometry": {
                    "type": "Point",
                    "coordinates": [
                        28357.22555123217,
                        37563.465076206645
                    ]
                },
                "properties": {
                    "type": "destination"
                }
            },
            {
                "type": "Feature",
                "geometry": {
                    "type": "Polygon",
                    "coordinates": [
                        [
                            [
                                28351.09025150005,
                                37537.85076765794
                            ],
                            [
                                28346.894424683756,
                                37546.72209810403
                            ],
                            [
                                28346.142173610137,
                                37547.97715319766
                            ],
                            [
                                28357.908030242183,
                                37540.84613415008
                            ],
                            [
                                28352.731217311335,
                                37533.264575449335
                            ],
                            [
                                28351.09025150005,
                                37537.85076765794
                            ]
                        ]
                    ]
                },
                "properties": {
                    "type": "mask"
                }
            }
        ]
    }
]